{
  "kind": "collectionType",
  "collectionName": "sliders",
  "info": {
    "name": "Slider",
    "description": ""
  },
  "options": {
    "increments": true,
    "timestamps": true,
    "draftAndPublish": true
  },
  "attributes": {
    "title": {
      "type": "string"
    },
    "text": {
      "type": "richtext"
    },
    "imageClassic": {
      "collection": "file",
      "via": "related",
      "allowedTypes": [
        "files",
        "images",
        "videos"
      ],
      "plugin": "upload",
      "required": true
    },
    "imageFull": {
      "collection": "file",
      "via": "related",
      "allowedTypes": [
        "files",
        "images",
        "videos"
      ],
      "plugin": "upload",
      "required": true
    },
    "imageMobile": {
      "collection": "file",
      "via": "related",
      "allowedTypes": [
        "files",
        "images",
        "videos"
      ],
      "plugin": "upload",
      "required": true
    },
    "type_image": {
      "type": "enumeration",
      "enum": [
        "ltr",
        "rtl"
      ]
    },
    "locales": {
      "collection": "locale",
      "via": "sliders",
      "dominant": true
    }
  }
}
